modelscope_agent/__init__.py
modelscope_agent/agent.py
modelscope_agent/agent_env_util.py
modelscope_agent/agents_registry.py
modelscope_agent/constants.py
modelscope_agent/schemas.py
modelscope_agent/task_center.py
modelscope_agent/version.py
modelscope_agent/agents/__init__.py
modelscope_agent/agents/agent_builder.py
modelscope_agent/agents/alpha_umi.py
modelscope_agent/agents/data_science_assistant.py
modelscope_agent/agents/gen_keyword.py
modelscope_agent/agents/multi_role_play.py
modelscope_agent/agents/role_play.py
modelscope_agent/agents/codexgraph_agent/__init__.py
modelscope_agent/agents/codexgraph_agent/cypher_agent.py
modelscope_agent/agents/codexgraph_agent/prompt.py
modelscope_agent/agents/codexgraph_agent/task/__init__.py
modelscope_agent/agents/codexgraph_agent/task/code_chat.py
modelscope_agent/agents/codexgraph_agent/task/code_debugger.py
modelscope_agent/agents/codexgraph_agent/task/code_general.py
modelscope_agent/agents/codexgraph_agent/utils/__init__.py
modelscope_agent/agents/codexgraph_agent/utils/code_utils.py
modelscope_agent/agents/codexgraph_agent/utils/cypher_utils.py
modelscope_agent/agents/codexgraph_agent/utils/prompt_utils.py
modelscope_agent/agents/mobile_agent_v2/__init__.py
modelscope_agent/agents/mobile_agent_v2/mobile_agent_v2.py
modelscope_agent/agents/mobile_agent_v2/prompt.py
modelscope_agent/callbacks/__init__.py
modelscope_agent/callbacks/base.py
modelscope_agent/callbacks/run_state.py
modelscope_agent/environment/__init__.py
modelscope_agent/environment/environment.py
modelscope_agent/environment/android_adb/__init__.py
modelscope_agent/environment/android_adb/android_adb_env.py
modelscope_agent/environment/android_adb/utils.py
modelscope_agent/environment/graph_database/__init__.py
modelscope_agent/environment/graph_database/build.py
modelscope_agent/environment/graph_database/graph_database.py
modelscope_agent/environment/graph_database/ast_search/__init__.py
modelscope_agent-0.7.2.dist-info/LICENSE
modelscope_agent-0.7.2.dist-info/METADATA
modelscope_agent-0.7.2.dist-info/WHEEL
modelscope_agent-0.7.2.dist-info/top_level.txt
modelscope_agent-0.7.2.dist-info/RECORD
