Metadata-Version: 2.1
Name: modelscope-agent
Version: 0.7.2
Summary: ModelScope Agent: Be a powerful models and tools agent based on ModelScope and open source LLM.
Home-page: https://github.com/modelscope/modelscope-agent
Author: Modelscope Team
Author-email: contact@modelscope.cn
License: Apache License 2.0
Keywords: python,agent,LLM,AIGC,qwen,ModelScope
License-File: LICENSE
Requires-Dist: dashscope>=1.20.1
Requires-Dist: faiss-cpu
Requires-Dist: grpcio
Requires-Dist: jieba
Requires-Dist: json5
Requires-Dist: jsonref
Requires-Dist: jupyter>=1.0.0
Requires-Dist: langchain
Requires-Dist: langchain-community
Requires-Dist: langchain-experimental
Requires-Dist: llama-index==0.10.29
Requires-Dist: llama-index-core==0.10.39.post1
Requires-Dist: llama-index-readers-json
Requires-Dist: llama-index-retrievers-bm25==0.1.5
Requires-Dist: modelscope[framework]>=1.16.0
Requires-Dist: openai
Requires-Dist: opencv-python
Requires-Dist: openpyxl
Requires-Dist: pdfminer.six
Requires-Dist: Pillow
Requires-Dist: pydantic>=2.3.0
Requires-Dist: pytest
Requires-Dist: pytest-mock
Requires-Dist: python-dotenv
Requires-Dist: requests>=2.32.3
Requires-Dist: seaborn
Requires-Dist: sentencepiece
Requires-Dist: tiktoken
Requires-Dist: unstructured
